gene_enrich/__init__.py
gene_enrich/enrich.py
gene_enrich/get_kegggenes.py
gene_enrich/plotting.py
gene_enrich-0.0.0.1.dist-info/METADATA
gene_enrich-0.0.0.1.dist-info/WHEEL
gene_enrich-0.0.0.1.dist-info/top_level.txt
gene_enrich-0.0.0.1.dist-info/RECORD
